MANIFEST.in
Makefile
README
mangler.py
setup.py
test/__init__.py
test/__init__.pyc
test/example.xml
test/nolink.xml
test/test_example.py
test/test_example.pyc
tiddlywebplugins/__init__.py
tiddlywebplugins/imrss.py
tiddlywebplugins.imrss.egg-info/PKG-INFO
tiddlywebplugins.imrss.egg-info/SOURCES.txt
tiddlywebplugins.imrss.egg-info/dependency_links.txt
tiddlywebplugins.imrss.egg-info/namespace_packages.txt
tiddlywebplugins.imrss.egg-info/not-zip-safe
tiddlywebplugins.imrss.egg-info/requires.txt
tiddlywebplugins.imrss.egg-info/top_level.txt