Metadata-Version: 1.0
Name: tiddlywebplugins.imrss
Version: 0.9.3
Summary: Allows you to import rss/atom feeds into tiddlers on your TiddlyWeb through a twanager command imrss. Also provides imrsswithtags which provides a mechanism to tag non-tagged rss feeds.
Home-page: http://pypi.python.org/pypi/tiddlywebplugins.imrss
Author: Jon Robson
Author-email: jdlrobson@gmail.com
License: UNKNOWN
Platform: Posix; MacOS X; Windows
